LICENSE
README.md
setup.py
autodoc/__init__.py
autodoc/apps.py
autodoc/utils.py
autodoc/management/__init__.py
autodoc/management/commands/__init__.py
autodoc/management/commands/autodoc_flow.py
autodoc/management/commands/autodoc_sequence.py
autodoc_django.egg-info/PKG-INFO
autodoc_django.egg-info/SOURCES.txt
autodoc_django.egg-info/dependency_links.txt
autodoc_django.egg-info/requires.txt
autodoc_django.egg-info/top_level.txt
contact/__init__.py
contact/admin.py
contact/apps.py
contact/forms.py
contact/models.py
contact/tests.py
contact/urls.py
contact/views.py
contact/migrations/0001_initial.py
contact/migrations/0002_auto_20160405_2155.py
contact/migrations/0003_subject_is_active.py
contact/migrations/0004_auto_20190814_1713.py
contact/migrations/0005_contact_its_budget.py
contact/migrations/0006_auto_20191008_1416.py
contact/migrations/0007_subject_order.py
contact/migrations/0008_auto_20210105_1353.py
contact/migrations/0009_auto_20210105_1354.py
contact/migrations/0010_auto_20240117_1933.py
contact/migrations/__init__.py
core/__init__.py
core/asgi.py
core/settings.py
core/urls.py
core/wsgi.py