Metadata-Version: 2.2
Name: autodoc-django
Version: 0.1.1
Summary: Provide an automatic documentation for Django's Apps
Home-page: https://github.com/GomesMarcos/autodoc-django
Author: Marcos Gomes
Author-email: gomes.marcosjf@gmail.com
Classifier: Programming Language :: Python :: 3
Classifier: License :: OSI Approved :: MIT License
Classifier: Operating System :: OS Independent
Requires-Python: >=3.6
License-File: LICENSE
Requires-Dist: asgiref>=3.8.1
Requires-Dist: Django>=4.2.19
Requires-Dist: python-decouple>=3.8
Requires-Dist: ruff>=0.7.1
Requires-Dist: sqlparse>=0.5.1
Dynamic: author
Dynamic: author-email
Dynamic: classifier
Dynamic: description
Dynamic: description-content-type
Dynamic: home-page
Dynamic: requires-dist
Dynamic: requires-python
Dynamic: summary
